esdbclient/__init__.py
esdbclient/asyncio_client.py
esdbclient/client.py
esdbclient/common.py
esdbclient/connection.py
esdbclient/connection_spec.py
esdbclient/events.py
esdbclient/exceptions.py
esdbclient/gossip.py
esdbclient/instrumentation/__init__.py
esdbclient/instrumentation/opentelemetry/__init__.py
esdbclient/instrumentation/opentelemetry/attributes.py
esdbclient/instrumentation/opentelemetry/grpc.py
esdbclient/instrumentation/opentelemetry/package.py
esdbclient/instrumentation/opentelemetry/spanners.py
esdbclient/instrumentation/opentelemetry/utils.py
esdbclient/instrumentation/opentelemetry/version.py
esdbclient/persistent.py
esdbclient/projections.py
esdbclient/protos/Grpc/cluster_pb2.py
esdbclient/protos/Grpc/cluster_pb2.pyi
esdbclient/protos/Grpc/cluster_pb2_grpc.py
esdbclient/protos/Grpc/code_pb2.py
esdbclient/protos/Grpc/code_pb2.pyi
esdbclient/protos/Grpc/code_pb2_grpc.py
esdbclient/protos/Grpc/gossip_pb2.py
esdbclient/protos/Grpc/gossip_pb2.pyi
esdbclient/protos/Grpc/gossip_pb2_grpc.py
esdbclient/protos/Grpc/persistent_pb2.py
esdbclient/protos/Grpc/persistent_pb2.pyi
esdbclient/protos/Grpc/persistent_pb2_grpc.py
esdbclient/protos/Grpc/projections_pb2.py
esdbclient/protos/Grpc/projections_pb2.pyi
esdbclient/protos/Grpc/projections_pb2_grpc.py
esdbclient/protos/Grpc/shared_pb2.py
esdbclient/protos/Grpc/shared_pb2.pyi
esdbclient/protos/Grpc/shared_pb2_grpc.py
esdbclient/protos/Grpc/status_pb2.py
esdbclient/protos/Grpc/status_pb2.pyi
esdbclient/protos/Grpc/status_pb2_grpc.py
esdbclient/protos/Grpc/streams_pb2.py
esdbclient/protos/Grpc/streams_pb2.pyi
esdbclient/protos/Grpc/streams_pb2_grpc.py
esdbclient/py.typed
esdbclient/streams.py
esdbclient-1.1.7.dist-info/LICENSE
esdbclient-1.1.7.dist-info/METADATA
esdbclient-1.1.7.dist-info/WHEEL
esdbclient-1.1.7.dist-info/RECORD
