Metadata-Version: 2.3
Name: esdbclient
Version: 1.1.7
Summary: Python gRPC Client for EventStoreDB
License: BSD 3-Clause
Author: John Bywater
Author-email: john.bywater@appropriatesoftware.net
Requires-Python: >=3.9,<4.0
Classifier: Development Status :: 5 - Production/Stable
Classifier: License :: OSI Approved :: BSD License
Classifier: License :: Other/Proprietary License
Classifier: Programming Language :: Python
Classifier: Programming Language :: Python :: 3
Classifier: Programming Language :: Python :: 3.9
Classifier: Programming Language :: Python :: 3.10
Classifier: Programming Language :: Python :: 3.11
Classifier: Programming Language :: Python :: 3.12
Classifier: Programming Language :: Python :: 3.13
Provides-Extra: opentelemetry
Requires-Dist: grpcio[protobuf] (>=1.71.0,<1.72)
Requires-Dist: opentelemetry-api (>=1.28.0,<2.0.0) ; extra == "opentelemetry"
Requires-Dist: opentelemetry-instrumentation (>=0.49b0,<0.50) ; extra == "opentelemetry"
Requires-Dist: opentelemetry-semantic-conventions (>=0.49b0,<0.50) ; extra == "opentelemetry"
Requires-Dist: typing_extensions
Project-URL: Homepage, https://github.com/pyeventsourcing/esdbclient
Project-URL: Repository, https://github.com/pyeventsourcing/esdbclient
